{
  "title": "2019/06/14 第2回 LT大会「2年生に伝えたいこと vol.02」",
  "description": "2019/06/14 第2回 LT大会「2年生に伝えたいこと vol.02」",
  "author": "村田 司",
  "tags": null,
  "category": "Lightning Talks",
  "thumbnail": null,
  "created_at": "2019-06-14 00:00:00",
  "updated_at": "2019-06-14 00:00:00",
  "bodyContent": "## 第2回 LT大会  \n\n### 「2年生に伝えたいこと vol.02」  \n\n日程：6月14日（金）  \n時間：18:30〜  \n場所：HAL大阪 163教室  \n\n[connpass](https://haltechclub.connpass.com/event/135109/)  \n\n1. Bootstrap is GOD／高田（3年/高度情報）\n2. Webエンジニア就職レポート／郭（秋2年/Web開発）\n3. VSCodeのお話／細見（3年/Web開発）\n4. NEは未来を手に入れる ／曹（3年/高度情報）",
  "bodyHtml": "<h2>第2回 LT大会</h2>\n<h3>「2年生に伝えたいこと vol.02」</h3>\n<p>日程：6月14日（金）<br>\n時間：18:30〜<br>\n場所：HAL大阪 163教室</p>\n<p><a href=\"https://haltechclub.connpass.com/event/135109/\">connpass</a></p>\n<ol>\n<li>Bootstrap is GOD／高田（3年/高度情報）</li>\n<li>Webエンジニア就職レポート／郭（秋2年/Web開発）</li>\n<li>VSCodeのお話／細見（3年/Web開発）</li>\n<li>NEは未来を手に入れる ／曹（3年/高度情報）</li>\n</ol>\n",
  "preview": "第2回 LT大会\n\n「2年生に伝えたいこと vol.02」\n\n日程：6月14日（金）\n時間：18:30〜\n場所：HAL大阪 163教室\n\nconnpass\n\nBootstrap is",
  "dir": "contents/json",
  "base": "2019-6-14-lt.json",
  "ext": ".json",
  "sourceBase": "2019-6-14-lt.md",
  "sourceExt": ".md"
}